metacore/__init__.py
metacore/abstract/__init__.py
metacore/abstract/exceptions/__init__.py
metacore/abstract/exceptions/traced_exceptions.py
metacore/meta/__init__.py
metacore/meta/classes/__init__.py
metacore/meta/classes/constants.py
metacore/meta/typing_utilities/__init__.py
metacore/meta/typing_utilities/errors.py
metacore/meta/typing_utilities/implements.py
metacore/meta/typing_utilities/utilities.py
metacore/meta/typing_utilities/annotations_processors/__init__.py
metacore/meta/typing_utilities/annotations_processors/errors.py
metacore/meta/typing_utilities/annotations_processors/known_types.py
metacore/meta/typing_utilities/annotations_processors/processors.py
sg_metacore-0.1.0a0.dist-info/licenses/LICENSE
sg_metacore-0.1.0a0.dist-info/METADATA
sg_metacore-0.1.0a0.dist-info/WHEEL
sg_metacore-0.1.0a0.dist-info/top_level.txt
sg_metacore-0.1.0a0.dist-info/RECORD
