Metadata-Version: 2.4
Name: sg-metacore
Version: 0.1.0a0
Summary: A sophisticated type system enhancement library for metaprogramming and runtime behavior modification
Author-email: Sébastien Gachoud <sebastien.gachoud@gmail.com>
License: MIT
Project-URL: Homepage, https://github.com/sgachoud/python_libs/tree/main/metacore
Project-URL: Repository, https://github.com/sgachoud/python_libs
Project-URL: Issues, https://github.com/sgachoud/python_libs/issues
Keywords: metaprogramming,type-system,annotations,constants,type-safety
Classifier: Development Status :: 3 - Alpha
Classifier: Intended Audience :: Developers
Classifier: License :: OSI Approved :: MIT License
Classifier: Programming Language :: Python :: 3
Classifier: Programming Language :: Python :: 3.12
Classifier: Topic :: Software Development :: Libraries :: Python Modules
Classifier: Typing :: Typed
Requires-Python: >=3.12
License-File: LICENSE
Provides-Extra: dev
Requires-Dist: pytest>=7.0; extra == "dev"
Requires-Dist: pytest-cov>=4.0; extra == "dev"
Dynamic: license-file
